vnrs-0.1.0.dist-info/METADATA
vnrs-0.1.0.dist-info/WHEEL
vnrs-0.1.0.dist-info/licenses/LICENSE
vnrs/optimize.py
vnrs/__init__.py
vnrs/__pycache__/optimize.cpython-311.pyc
vnrs/__pycache__/__init__.cpython-311.pyc
vnrs/vnrs.cp311-win_amd64.pyd
vnrs-0.1.0.dist-info/RECORD
